setup.py
graph_data_source.egg-info/PKG-INFO
graph_data_source.egg-info/SOURCES.txt
graph_data_source.egg-info/dependency_links.txt
graph_data_source.egg-info/not-zip-safe
graph_data_source.egg-info/top_level.txt
gutenberg/__init__.py
gutenberg/api.py
lexitheras/__init__.py
lexitheras/api.py
tests/__init__.py
tests/gutenberg/__init__.py
tests/gutenberg/test_api.py