Metadata-Version: 2.1
Name: graph-data-source
Version: 0.0.51
Summary: An abstraction layer that ports various data into Antiqua
Home-page: https://github.com/QubitPi/Antiqua/tree/master/graph-data-source
Author: Jiaqi Liu
Author-email: jack20220723@gmail.com
License: Apache-2.0
Requires-Python: >=3.10
